{
  "Sender": {
    "ContactId": 0,
    "Cuid": "49cb518a-6966-4fbb-ac0e-e27a1115bf29",
    "Name": "Heinrich G. Elsigan",
    "Email": "he@area23.at",
    "Mobile": "+43 650 7527928",
    "Address": "Theresianumgasse 6/28, 1040 Wien",
    "ContactImage": null,
    "MsgType": 0,
    "Message": "room_08200827_he.json",
    "Hash": "6bFfDC",
    "Md5Hash": "b08c701456ddcfe7a2a1c61b5518f5bf",
    "EnCodingType": 64
  },
  "Recipients": [
    {
      "ContactId": 36,
      "Cuid": "1a784497-0826-4b5d-a8a9-fd61a3e2e09b",
      "Name": "Markus Norbert Stumpfel",
      "Email": "markus.stumpfel2007@protonmail.com",
      "Mobile": "+43 664 5217354",
      "Address": "",
      "ContactImage": null,
      "MsgType": 1,
      "Message": "room_08200827_he.json",
      "Hash": "6bFfDC",
      "Md5Hash": "",
      "EnCodingType": 64
    }
  ],
  "TContent": "",
  "CRoom": {
    "ChatRuid": "c00fa154-3e67-4c45-9b53-55fb139dda52",
    "ChatRoomNr": "room_08200827_he.json",
    "TicksLong": [
      638912752534002118,
      638912752826890281,
      638912753314668238,
      638912755302944148,
      638912755560318666
    ],
    "LastPushed": "2025-08-20T08:32:36.0318666+02:00",
    "LastPolled": "2025-08-20T08:27:33.4002118+02:00",
    "InvitedEmails": [
      "markus.stumpfel2007@protonmail.com",
      "he@area23.at"
    ],
    "MsgType": 0,
    "Message": "",
    "Hash": "",
    "Md5Hash": "",
    "EnCodingType": 64
  },
  "MsgType": 1,
  "Message": "room_08200827_he.json",
  "Hash": "6CDgbXFf",
  "Md5Hash": "48987f82e0bda9b1c581c7c950409c20",
  "EnCodingType": 64
}